vupysolr/__init__.py
vupysolr/__main__.py
vupysolr/base.py
vupysolr/docs.py
vupysolr/utils.py
vupysolr-0.2.2.dist-info/LICENSE
vupysolr-0.2.2.dist-info/METADATA
vupysolr-0.2.2.dist-info/WHEEL
vupysolr-0.2.2.dist-info/entry_points.txt
vupysolr-0.2.2.dist-info/top_level.txt
vupysolr-0.2.2.dist-info/RECORD
