Metadata-Version: 2.1
Name: vupysolr
Version: 0.2.2
Summary: Access Solr stored VuFind records.
Home-page: https://github.com/herreio/vupysolr
Author: Donatus Herre
Author-email: donatus.herre@slub-dresden.de
License: GPLv3
License-File: LICENSE
Requires-Dist: pysolr
Requires-Dist: pymarc
Requires-Dist: python-dateutil
Requires-Dist: requests
